{
  "generator-jhipster": {
    "applicationType": "monolith",
    "gitCompany": "",
    "baseName": "jhipsterSampleApplication",
    "packageName": "io.github.jhipster.application",
    "packageFolder": "io/github/jhipster/application",
    "serverPort": 8080,
    "serviceDiscoveryType": false,
    "authenticationType": "jwt",
    "uaaBaseName": "../uaa",
    "cacheProvider": "ehcache",
    "enableHibernateCache": true,
    "websocket": false,
    "databaseType": "sql",
    "devDatabaseType": "h2Disk",
    "prodDatabaseType": "mysql",
    "searchEngine": false,
    "enableSwaggerCodegen": false,
    "messageBroker": false,
    "buildTool": "maven",
    "useSass": false,
    "clientPackageManager": "npm",
    "testFrameworks": [],
    "enableTranslation": false,
    "nativeLanguage": "en",
    "languages": [
      "en"
    ],
    "clientFramework": "angularX",
    "jhiPrefix": "jhi",
    "jhipsterVersion": "5.8.2",
    "jwtSecretKey": "Y2Q0MWIzZGVkN2Y3YThmNzM1MjMyMjQzZWY5ODhiNTZiNjgyNzk2NmFiZWM1ZTQ0NTA4ZTNkMTM3YWFhNjQ2NzExYzQ0ZDNjNTlkMjYwYWM5OWFlMTMxMWJiOWY2NmViOTJjMzczYzBkZWQ1OGNkMmUwZGQ4YmNiM2IzYWU1MTE=",
    "entitySuffix": "",
    "dtoSuffix": "DTO",
    "otherModules": []
  },
  "git-provider": "GitHub",
  "git-company": "WillParken",
  "repository-name": "jhipster-sample-application"
}